{"cameraMode":{"drawMode":0,"name":"Shaded","section":"Shading Mode"},"sceneLighting":true,"audioPlay":false,"sceneViewState":{"m_AlwaysRefresh":false,"showFog":true,"showSkybox":true,"showFlares":true,"showImageEffects":true,"showParticleSystems":true,"showVisualEffectGraphs":true,"m_FxEnabled":true},"in2DMode":false,"pivot":{"x":0.0,"y":0.5999999046325684,"z":0.0},"rotation":{"x":0.21078605949878694,"y":0.469979465007782,"z":-0.11666117608547211,"w":0.8491662740707398},"size":12.12435531616211,"orthographic":false}